README.md
setup.py
TestTarifaFedex.egg-info/PKG-INFO
TestTarifaFedex.egg-info/SOURCES.txt
TestTarifaFedex.egg-info/dependency_links.txt
TestTarifaFedex.egg-info/top_level.txt
src/__init__.py
src/main.py
src/saludo.py